{
  "name": "contact-form",
  "label": "Contact Form",
  "display": "block",
  "sub_fields": [
    {
      "key": "field_contact_heading",
      "label": "Heading",
      "name": "heading",
      "type": "text"
    },
    {
      "key": "field_contact_description",
      "label": "Description",
      "name": "description",
      "type": "textarea"
    },
    {
      "key": "field_contact_form_id",
      "label": "Form ID (Fluent Forms)",
      "name": "form_id",
      "type": "text",
      "required": true,
      "instructions": "Enter a Fluent Forms ID (e.g., 3) or a full shortcode like [fluentform id=\"3\"]."
    },
    {
      "key": "field_contact_bg_color",
      "label": "Background Color",
      "name": "background_color",
      "type": "color_picker",
      "default_value": "#ffffff"
    }
  ]
}
